{
  "bgm": [
    "BGM_03"
  ],
  "bgp": [
    "BG_019_A0"
  ],
  "egp": [],
  "cid": [
    "NAD"
  ],
  "label": [
    {
      "name": "SCR_L_YC_CV3_001_START",
      "line": 0
    },
    {
      "name": "SCR_L_YC_CV3_001_1_1",
      "line": 23
    },
    {
      "name": "SCR_L_YC_CV3_001_1_2",
      "line": 34
    },
    {
      "name": "SCR_L_YC_CV3_001_1_3",
      "line": 47
    }
  ],
  "message": [
    {
      "function": "XAUTOSAVE_SCENE",
      "argument": [],
      "name": "",
      "msgidx": -1,
      "voice": "",
      "vid": "",
      "value": "",
      "said": ""
    },
    {
      "function": "XCLR",
      "argument": [],
      "name": "",
      "msgidx": -1,
      "voice": "",
      "vid": "",
      "value": "",
      "said": ""
    },
    {
      "function": "XFADE",
      "argument": [
        "XFTS,MaskTexture.None,0",
        "XFOT,0.5"
      ],
      "name": "",
      "msgidx": -1,
      "voice": "",
      "vid": "",
      "value": "",
      "said": ""
    },
    {
      "function": "XWXB",
      "argument": [],
      "name": "",
      "msgidx": -1,
      "voice": "",
      "vid": "",
      "value": "",
      "said": ""
    },
    {
      "function": "SNSE",
      "argument": [
        "NSE_OFF",
        "0"
      ],
      "name": "",
      "msgidx": -1,
      "voice": "",
      "vid": "",
      "value": "",
      "said": ""
    },
    {
      "function": "XWXB",
      "argument": [],
      "name": "",
      "msgidx": -1,
      "voice": "",
      "vid": "",
      "value": "",
      "said": ""
    },
    {
      "function": "XLCYDRAW",
      "argument": [
        "XLCYLOAD,Lucy.Type.BACK,BG_019_A0",
        "XLCYFADE,0,0.001"
      ],
      "name": "",
      "msgidx": -1,
      "voice": "",
      "vid": "",
      "value": "",
      "said": ""
    },
    {
      "function": "XLCYDRAW",
      "argument": [
        "XLCYFIND,FindType.SP_C",
        "XLCYLOAD,Lucy.Type.BUST,BU_NAD_DEF_0_NML",
        "XLCYLOAD,Lucy.Type.SP_L,SP_OFF",
        "XLCYLOAD,Lucy.Type.SP_R,SP_OFF",
        "XLCYLOAD,Lucy.Type.SP_C,SP_OFF",
        "XLCYFADE,0,0.25"
      ],
      "name": "",
      "msgidx": -1,
      "voice": "",
      "vid": "",
      "value": "",
      "said": ""
    },
    {
      "function": "SBGM",
      "argument": [
        "BGM_03"
      ],
      "name": "",
      "msgidx": -1,
      "voice": "",
      "vid": "",
      "value": "",
      "said": ""
    },
    {
      "function": "SESE",
      "argument": [
        "ESE_OFF",
        "0"
      ],
      "name": "",
      "msgidx": -1,
      "voice": "",
      "vid": "",
      "value": "",
      "said": ""
    },
    {
      "function": "XMON",
      "argument": [],
      "name": "",
      "msgidx": -1,
      "voice": "",
      "vid": "",
      "value": "",
      "said": ""
    },
    {
      "function": "XFADE",
      "argument": [
        "XFTS,MaskTexture.None,0",
        "XFIN,0.5"
      ],
      "name": "",
      "msgidx": -1,
      "voice": "",
      "vid": "",
      "value": "",
      "said": ""
    },
    {
      "function": "XEOB",
      "argument": [
        "EffectType.CINEMA",
        "0",
        "0",
        "0",
        "255",
        "0.2",
        "165"
      ],
      "name": "",
      "msgidx": -1,
      "voice": "",
      "vid": "",
      "value": "",
      "said": ""
    },
    {
      "function": "XABL",
      "argument": [
        "ID_NAD",
        "FP_TALK_M"
      ],
      "name": "",
      "msgidx": -1,
      "voice": "",
      "vid": "",
      "value": "",
      "said": ""
    },
    {
      "function": "XLCYDRAW",
      "argument": [
        "XLCYFIND,FindType.SP_C",
        "XLCYLOAD,Lucy.Type.BUST,BU_NAD_DEF_0_NML",
        "XLCYLOAD,Lucy.Type.SP_L,SP_OFF",
        "XLCYLOAD,Lucy.Type.SP_R,SP_OFF",
        "XLCYLOAD,Lucy.Type.SP_C,SP_OFF",
        "XLCYFADE,0,0.25"
      ],
      "name": "",
      "msgidx": -1,
      "voice": "",
      "vid": "",
      "value": "",
      "said": ""
    },
    {
      "function": "XMESS",
      "argument": [
        "そういえば飯ごうってあったよね？",
        "昔はキャンプといえば、あのイメージが",
        "あったけど、もう使われてないのかな？"
      ],
      "name": "各務原なでしこ",
      "msgidx": 0,
      "voice": "NAD_3485_0001",
      "vid": "VID_NAD",
      "value": "",
      "said": ""
    },
    {
      "function": "XWCR",
      "argument": [],
      "name": "",
      "msgidx": -1,
      "voice": "",
      "vid": "",
      "value": "",
      "said": ""
    },
    {
      "function": "XMESS",
      "argument": [
        "いや、今でも使ってる人いるよ。"
      ],
      "name": "志摩リン（収録除外）",
      "msgidx": 1,
      "voice": "",
      "vid": "",
      "value": "",
      "said": ""
    },
    {
      "function": "XWCR",
      "argument": [],
      "name": "",
      "msgidx": -1,
      "voice": "",
      "vid": "",
      "value": "",
      "said": ""
    },
    {
      "function": "XLCYDRAW",
      "argument": [
        "XLCYFIND,FindType.SP_C",
        "XLCYLOAD,Lucy.Type.BUST,BU_NAD_DEF_0_SML",
        "XLCYLOAD,Lucy.Type.SP_L,SP_OFF",
        "XLCYLOAD,Lucy.Type.SP_R,SP_OFF",
        "XLCYLOAD,Lucy.Type.SP_C,SP_OFF",
        "XLCYFADE,0,0.25"
      ],
      "name": "",
      "msgidx": -1,
      "voice": "",
      "vid": "",
      "value": "",
      "said": ""
    },
    {
      "function": "XMESS",
      "argument": [
        "へえ、そうなんだぁ。",
        "いつか飯ごう使って、ごはん炊いてみる？"
      ],
      "name": "各務原なでしこ",
      "msgidx": 2,
      "voice": "NAD_3486_0002",
      "vid": "VID_NAD",
      "value": "",
      "said": ""
    },
    {
      "function": "XWAI",
      "argument": [],
      "name": "",
      "msgidx": -1,
      "voice": "",
      "vid": "",
      "value": "",
      "said": ""
    },
    {
      "function": "MSTD",
      "argument": [
        "SCR_MENU_0",
        "0",
        "LSCR_MENU_0",
        "「ああ、やってみようか」,M_ON,SCR_L_YC_CV3_001_1_1",
        "「ごはんどころか」,M_ON,SCR_L_YC_CV3_001_1_2",
        "「パックごはんでよくない？」,M_ON,SCR_L_YC_CV3_001_1_3"
      ],
      "name": "",
      "msgidx": -1,
      "voice": "",
      "vid": "",
      "value": "",
      "said": ""
    },
    {
      "function": "XCLR",
      "argument": [],
      "name": "",
      "msgidx": -1,
      "voice": "",
      "vid": "",
      "value": "",
      "said": ""
    },
    {
      "function": "XCCTER",
      "argument": [
        "CC_1",
        "C3_1_1ST_S1_TP",
        "Ccter.PLS"
      ],
      "name": "",
      "msgidx": -1,
      "voice": "",
      "vid": "",
      "value": "",
      "said": ""
    },
    {
      "function": "XMESS",
      "argument": [
        "ああ、やってみようか。",
        "何だか、懐かしい感じするし。"
      ],
      "name": "志摩リン（収録除外）",
      "msgidx": 3,
      "voice": "",
      "vid": "",
      "value": "",
      "said": ""
    },
    {
      "function": "XWCR",
      "argument": [],
      "name": "",
      "msgidx": -1,
      "voice": "",
      "vid": "",
      "value": "",
      "said": ""
    },
    {
      "function": "XLCYDRAW",
      "argument": [
        "XLCYFIND,FindType.SP_C",
        "XLCYLOAD,Lucy.Type.BUST,BU_NAD_DEF_0_LAU",
        "XLCYLOAD,Lucy.Type.SP_L,SP_OFF",
        "XLCYLOAD,Lucy.Type.SP_R,SP_OFF",
        "XLCYLOAD,Lucy.Type.SP_C,SP_OFF",
        "XLCYFADE,0,0.25"
      ],
      "name": "",
      "msgidx": -1,
      "voice": "",
      "vid": "",
      "value": "",
      "said": ""
    },
    {
      "function": "XMESS",
      "argument": [
        "じゃ決まりだね！",
        "えへへ、楽しみだなぁ。"
      ],
      "name": "各務原なでしこ",
      "msgidx": 4,
      "voice": "NAD_3487_0003",
      "vid": "VID_NAD",
      "value": "",
      "said": ""
    },
    {
      "function": "XWCR",
      "argument": [],
      "name": "",
      "msgidx": -1,
      "voice": "",
      "vid": "",
      "value": "",
      "said": ""
    },
    {
      "function": "XEOE",
      "argument": [
        "EffectType.CINEMA",
        "0.2"
      ],
      "name": "",
      "msgidx": -1,
      "voice": "",
      "vid": "",
      "value": "",
      "said": ""
    },
    {
      "function": "XFADE",
      "argument": [
        "XFED,0.5"
      ],
      "name": "",
      "msgidx": -1,
      "voice": "",
      "vid": "",
      "value": "",
      "said": ""
    },
    {
      "function": "XCLR",
      "argument": [],
      "name": "",
      "msgidx": -1,
      "voice": "",
      "vid": "",
      "value": "",
      "said": ""
    },
    {
      "function": "XEOS",
      "argument": [],
      "name": "",
      "msgidx": -1,
      "voice": "",
      "vid": "",
      "value": "",
      "said": ""
    },
    {
      "function": "XCLR",
      "argument": [],
      "name": "",
      "msgidx": -1,
      "voice": "",
      "vid": "",
      "value": "",
      "said": ""
    },
    {
      "function": "XCCTER",
      "argument": [
        "CC_1",
        "C3_1_1ST_S2_TP",
        "Ccter.PLS"
      ],
      "name": "",
      "msgidx": -1,
      "voice": "",
      "vid": "",
      "value": "",
      "said": ""
    },
    {
      "function": "XMESS",
      "argument": [
        "ごはんどころか、",
        "あれでプリン作る人も",
        "いるらしいぞ。"
      ],
      "name": "志摩リン（収録除外）",
      "msgidx": 5,
      "voice": "",
      "vid": "",
      "value": "",
      "said": ""
    },
    {
      "function": "XWCR",
      "argument": [],
      "name": "",
      "msgidx": -1,
      "voice": "",
      "vid": "",
      "value": "",
      "said": ""
    },
    {
      "function": "XLCYDRAW",
      "argument": [
        "XLCYFIND,FindType.SP_C",
        "XLCYLOAD,Lucy.Type.BUST,BU_NAD_DEF_1_LAU",
        "XLCYLOAD,Lucy.Type.SP_L,SP_OFF",
        "XLCYLOAD,Lucy.Type.SP_R,SP_OFF",
        "XLCYLOAD,Lucy.Type.SP_C,SP_OFF",
        "XLCYFADE,0,0.25"
      ],
      "name": "",
      "msgidx": -1,
      "voice": "",
      "vid": "",
      "value": "",
      "said": ""
    },
    {
      "function": "XMESS",
      "argument": [
        "えっ、プリン！？",
        "作りたい！",
        "私も作ってみたい！"
      ],
      "name": "各務原なでしこ",
      "msgidx": 6,
      "voice": "NAD_3488_0004",
      "vid": "VID_NAD",
      "value": "",
      "said": ""
    },
    {
      "function": "XWCR",
      "argument": [],
      "name": "",
      "msgidx": -1,
      "voice": "",
      "vid": "",
      "value": "",
      "said": ""
    },
    {
      "function": "XMESS",
      "argument": [
        "（思った通りの反応だな）"
      ],
      "name": "志摩リン（非収録）",
      "msgidx": 7,
      "voice": "",
      "vid": "",
      "value": "",
      "said": ""
    },
    {
      "function": "XWCR",
      "argument": [],
      "name": "",
      "msgidx": -1,
      "voice": "",
      "vid": "",
      "value": "",
      "said": ""
    },
    {
      "function": "XEOE",
      "argument": [
        "EffectType.CINEMA",
        "0.2"
      ],
      "name": "",
      "msgidx": -1,
      "voice": "",
      "vid": "",
      "value": "",
      "said": ""
    },
    {
      "function": "XFADE",
      "argument": [
        "XFED,0.5"
      ],
      "name": "",
      "msgidx": -1,
      "voice": "",
      "vid": "",
      "value": "",
      "said": ""
    },
    {
      "function": "XCLR",
      "argument": [],
      "name": "",
      "msgidx": -1,
      "voice": "",
      "vid": "",
      "value": "",
      "said": ""
    },
    {
      "function": "XEOS",
      "argument": [],
      "name": "",
      "msgidx": -1,
      "voice": "",
      "vid": "",
      "value": "",
      "said": ""
    },
    {
      "function": "XCLR",
      "argument": [],
      "name": "",
      "msgidx": -1,
      "voice": "",
      "vid": "",
      "value": "",
      "said": ""
    },
    {
      "function": "XCCTER",
      "argument": [
        "CC_1",
        "C3_1_1ST_S3_TP",
        "Ccter.PLS"
      ],
      "name": "",
      "msgidx": -1,
      "voice": "",
      "vid": "",
      "value": "",
      "said": ""
    },
    {
      "function": "XMESS",
      "argument": [
        "パックごはんでよくない？",
        "変に焦げたりしないし。"
      ],
      "name": "志摩リン（収録除外）",
      "msgidx": 8,
      "voice": "",
      "vid": "",
      "value": "",
      "said": ""
    },
    {
      "function": "XWCR",
      "argument": [],
      "name": "",
      "msgidx": -1,
      "voice": "",
      "vid": "",
      "value": "",
      "said": ""
    },
    {
      "function": "XLCYDRAW",
      "argument": [
        "XLCYFIND,FindType.SP_C",
        "XLCYLOAD,Lucy.Type.BUST,BU_NAD_DEF_0_SML",
        "XLCYLOAD,Lucy.Type.SP_L,SP_OFF",
        "XLCYLOAD,Lucy.Type.SP_R,SP_OFF",
        "XLCYLOAD,Lucy.Type.SP_C,SP_OFF",
        "XLCYFADE,0,0.25"
      ],
      "name": "",
      "msgidx": -1,
      "voice": "",
      "vid": "",
      "value": "",
      "said": ""
    },
    {
      "function": "XMESS",
      "argument": [
        "もしお焦げが出来たら、",
        "中華スープに入れて食べない？",
        "きっとおいしいよ！"
      ],
      "name": "各務原なでしこ",
      "msgidx": 9,
      "voice": "NAD_3489_0005",
      "vid": "VID_NAD",
      "value": "",
      "said": ""
    },
    {
      "function": "XWCR",
      "argument": [],
      "name": "",
      "msgidx": -1,
      "voice": "",
      "vid": "",
      "value": "",
      "said": ""
    },
    {
      "function": "XMESS",
      "argument": [
        "ああ、その手があったか。"
      ],
      "name": "志摩リン（収録除外）",
      "msgidx": 10,
      "voice": "",
      "vid": "",
      "value": "",
      "said": ""
    },
    {
      "function": "XWCR",
      "argument": [],
      "name": "",
      "msgidx": -1,
      "voice": "",
      "vid": "",
      "value": "",
      "said": ""
    },
    {
      "function": "XEOE",
      "argument": [
        "EffectType.CINEMA",
        "0.2"
      ],
      "name": "",
      "msgidx": -1,
      "voice": "",
      "vid": "",
      "value": "",
      "said": ""
    },
    {
      "function": "XFADE",
      "argument": [
        "XFED,0.5"
      ],
      "name": "",
      "msgidx": -1,
      "voice": "",
      "vid": "",
      "value": "",
      "said": ""
    },
    {
      "function": "XCLR",
      "argument": [],
      "name": "",
      "msgidx": -1,
      "voice": "",
      "vid": "",
      "value": "",
      "said": ""
    },
    {
      "function": "XEOS",
      "argument": [],
      "name": "",
      "msgidx": -1,
      "voice": "",
      "vid": "",
      "value": "",
      "said": ""
    }
  ]
}